[[{"location":"C:\\Users\\Alex\\.m2\\repository\\org\\eclipse\\rdf4j\\rdf4j-rio-api\\2.2\\rdf4j-rio-api-2.2.jar","type":"JAR","hints":{}},"org.eclipse.rdf4j:rdf4j-rio-api:2.2.0"],[{"location":"C:\\Program Files\\Java\\jdk1.8.0_25","type":"JRE","hints":{"EXECUTION_ENVIRONMENT":"JavaSE-1.8"}},"jre:jre:1.8.0"],[{"location":"C:\\Users\\Alex\\.m2\\repository\\org\\eclipse\\rdf4j\\rdf4j-query\\2.2\\rdf4j-query-2.2.jar","type":"JAR","hints":{}},"org.eclipse.rdf4j:rdf4j-query:2.2.0"],[{"location":"C:\\Users\\Alex\\Desktop\\Studium\\Wirtschaftsinfo\\Bachelorarbeit\\GitHub\\rdf4j\\rdf4j-implementation","type":"PROJECT","hints":{"PROJECT_NAME":"rdf4j-implementation"}},"org.example:rdf4j-implementation:0.0.1"],[{"location":"C:\\Users\\Alex\\.m2\\repository\\org\\eclipse\\rdf4j\\rdf4j-model\\2.2\\rdf4j-model-2.2.jar","type":"JAR","hints":{}},"org.eclipse.rdf4j:rdf4j-model:2.2.0"],[{"location":"C:\\Users\\Alex\\.m2\\repository\\org\\eclipse\\rdf4j\\rdf4j-repository-api\\2.2\\rdf4j-repository-api-2.2.jar","type":"JAR","hints":{}},"org.eclipse.rdf4j:rdf4j-repository-api:2.2.0"]]